pynasour/__init__.py
pynasour/constants.py
pynasour/enemy.py
pynasour/main.py
pynasour/music.py
pynasour/player.py
pynasour/utils.py
pynasour/asset/asset.pyxel
pynasour/asset/score.txt
pynasour-1.1.1.dist-info/LICENSE
pynasour-1.1.1.dist-info/METADATA
pynasour-1.1.1.dist-info/WHEEL
pynasour-1.1.1.dist-info/entry_points.txt
pynasour-1.1.1.dist-info/top_level.txt
pynasour-1.1.1.dist-info/RECORD
