Metadata-Version: 2.1
Name: pynasour
Version: 1.1.1
Summary: chrome dino clone in python 3
Home-page: https://github.com/dannyso16/pynasour
Author: dannyso16
License: MIT License
Platform: UNKNOWN
Requires-Python: >=3.6.8
License-File: LICENSE
Requires-Dist: pyxel (==1.1.8)
